{
  "id": "br-public-holidays",
  "name": "巴西公众假期",
  "category": "holidays",
  "name_en": "Brazil Public Holidays",
  "subcategory": "公众假期",
  "subcategory_en": "Public Holidays",
  "description": "巴西全国性公众假期安排，包含联邦假日和州级差异。",
  "description_en": "Brazil public holidays, including federal and state-level variations.",
  "icon": "🇧🇷",
  "tags": [
    "巴西",
    "公众假期",
    "节假日"
  ],
  "tags_en": [
    "Brazil",
    "Public Holidays"
  ],
  "maintainer": "official",
  "source_url": "https://www.gov.br/pt-br/calendario",
  "subscriber_count": 10000,
  "rating": 4.2,
  "rating_count": 250,
  "events": [
    {
      "id": "br-holiday-2025-new-years-day-01-01-public",
      "name": "Confraternização Universal",
      "name_en": "New Year's Day",
      "date": "2025-01-01",
      "end_date": "2025-01-01",
      "timezone": "America/Sao_Paulo",
      "type": "event",
      "year": 2025,
      "description": "Confraternização Universal（巴西公众假期）",
      "description_en": "New Year's Day (Brazil Public Holidays)",
      "url": "https://www.gov.br/pt-br/calendario",
      "status": "completed",
      "last_verified": "2026-06-07",
      "verified_by": "auto",
      "details": {
        "假期类型": "Public",
        "固定日期": "否",
        "全国通用": "是"
      },
      "name_zh": "元旦",
      "description_zh": "元旦（巴西公众假期）"
    },
    {
      "id": "br-holiday-2025-carnival-03-03-bank",
      "name": "Carnaval",
      "name_en": "Carnival",
      "date": "2025-03-03",
      "end_date": "2025-03-03",
      "timezone": "America/Sao_Paulo",
      "type": "event",
      "year": 2025,
      "description": "Carnaval（巴西公众假期）",
      "description_en": "Carnival (Brazil Public Holidays)",
      "url": "https://www.gov.br/pt-br/calendario",
      "status": "completed",
      "last_verified": "2026-06-07",
      "verified_by": "auto",
      "details": {
        "假期类型": "Bank, Optional",
        "固定日期": "否",
        "全国通用": "是"
      },
      "name_zh": "狂欢节",
      "description_zh": "狂欢节（巴西公众假期）"
    },
    {
      "id": "br-holiday-2025-carnival-03-04-bank",
      "name": "Carnaval",
      "name_en": "Carnival",
      "date": "2025-03-04",
      "end_date": "2025-03-04",
      "timezone": "America/Sao_Paulo",
      "type": "event",
      "year": 2025,
      "description": "Carnaval（巴西公众假期）",
      "description_en": "Carnival (Brazil Public Holidays)",
      "url": "https://www.gov.br/pt-br/calendario",
      "status": "completed",
      "last_verified": "2026-06-07",
      "verified_by": "auto",
      "details": {
        "假期类型": "Bank, Optional",
        "固定日期": "否",
        "全国通用": "是"
      },
      "name_zh": "狂欢节",
      "description_zh": "狂欢节（巴西公众假期）"
    },
    {
      "id": "br-holiday-2025-good-friday-04-18-public",
      "name": "Sexta-feira Santa",
      "name_en": "Good Friday",
      "date": "2025-04-18",
      "end_date": "2025-04-18",
      "timezone": "America/Sao_Paulo",
      "type": "event",
      "year": 2025,
      "description": "Sexta-feira Santa（巴西公众假期）",
      "description_en": "Good Friday (Brazil Public Holidays)",
      "url": "https://www.gov.br/pt-br/calendario",
      "status": "completed",
      "last_verified": "2026-06-07",
      "verified_by": "auto",
      "details": {
        "假期类型": "Public",
        "固定日期": "否",
        "全国通用": "是"
      },
      "name_zh": "耶稣受难日",
      "description_zh": "耶稣受难日（巴西公众假期）"
    },
    {
      "id": "br-holiday-2025-easter-sunday-04-20-public",
      "name": "Domingo de Páscoa",
      "name_en": "Easter Sunday",
      "date": "2025-04-20",
      "end_date": "2025-04-20",
      "timezone": "America/Sao_Paulo",
      "type": "event",
      "year": 2025,
      "description": "Domingo de Páscoa（巴西公众假期）",
      "description_en": "Easter Sunday (Brazil Public Holidays)",
      "url": "https://www.gov.br/pt-br/calendario",
      "status": "completed",
      "last_verified": "2026-06-07",
      "verified_by": "auto",
      "details": {
        "假期类型": "Public",
        "固定日期": "否",
        "全国通用": "是"
      },
      "name_zh": "复活节",
      "description_zh": "复活节（巴西公众假期）"
    },
    {
      "id": "br-holiday-2025-tiradentes-04-21-public",
      "name": "Dia de Tiradentes",
      "name_en": "Tiradentes",
      "date": "2025-04-21",
      "end_date": "2025-04-21",
      "timezone": "America/Sao_Paulo",
      "type": "event",
      "year": 2025,
      "description": "Dia de Tiradentes（巴西公众假期）",
      "description_en": "Tiradentes (Brazil Public Holidays)",
      "url": "https://www.gov.br/pt-br/calendario",
      "status": "completed",
      "last_verified": "2026-06-07",
      "verified_by": "auto",
      "details": {
        "假期类型": "Public",
        "固定日期": "否",
        "全国通用": "是"
      },
      "name_zh": "蒂拉登特斯日",
      "description_zh": "蒂拉登特斯日（巴西公众假期）"
    },
    {
      "id": "br-holiday-2025-labour-day-05-01-public",
      "name": "Dia do Trabalhador",
      "name_en": "Labour Day",
      "date": "2025-05-01",
      "end_date": "2025-05-01",
      "timezone": "America/Sao_Paulo",
      "type": "event",
      "year": 2025,
      "description": "Dia do Trabalhador（巴西公众假期）",
      "description_en": "Labour Day (Brazil Public Holidays)",
      "url": "https://www.gov.br/pt-br/calendario",
      "status": "completed",
      "last_verified": "2026-06-07",
      "verified_by": "auto",
      "details": {
        "假期类型": "Public",
        "固定日期": "否",
        "全国通用": "是"
      },
      "name_zh": "劳动节",
      "description_zh": "劳动节（巴西公众假期）"
    },
    {
      "id": "br-holiday-2025-corpus-christi-06-19-public",
      "name": "Corpus Christi",
      "name_en": "Corpus Christi",
      "date": "2025-06-19",
      "end_date": "2025-06-19",
      "timezone": "America/Sao_Paulo",
      "type": "event",
      "year": 2025,
      "description": "Corpus Christi（巴西公众假期）",
      "description_en": "Corpus Christi (Brazil Public Holidays)",
      "url": "https://www.gov.br/pt-br/calendario",
      "status": "completed",
      "last_verified": "2026-06-07",
      "verified_by": "auto",
      "details": {
        "假期类型": "Public",
        "固定日期": "否",
        "全国通用": "是"
      },
      "name_zh": "圣体节",
      "description_zh": "圣体节（巴西公众假期）"
    },
    {
      "id": "br-holiday-2025-constitutionalist-revolution-of-1932-07-09-br-sp",
      "name": "Revolução Constitucionalista de 1932",
      "name_en": "Constitutionalist Revolution of 1932",
      "date": "2025-07-09",
      "end_date": "2025-07-09",
      "timezone": "America/Sao_Paulo",
      "type": "event",
      "year": 2025,
      "description": "Revolução Constitucionalista de 1932（巴西公众假期）",
      "description_en": "Constitutionalist Revolution of 1932 (Brazil Public Holidays)",
      "url": "https://www.gov.br/pt-br/calendario",
      "status": "completed",
      "last_verified": "2026-06-07",
      "verified_by": "auto",
      "details": {
        "假期类型": "Public",
        "固定日期": "否",
        "全国通用": "否",
        "适用地区": "BR-SP"
      },
      "name_zh": "1932年宪政革命纪念日",
      "description_zh": "1932年宪政革命纪念日（巴西公众假期）"
    },
    {
      "id": "br-holiday-2025-independence-day-09-07-public",
      "name": "Dia da Independência",
      "name_en": "Independence Day",
      "date": "2025-09-07",
      "end_date": "2025-09-07",
      "timezone": "America/Sao_Paulo",
      "type": "event",
      "year": 2025,
      "description": "Dia da Independência（巴西公众假期）",
      "description_en": "Independence Day (Brazil Public Holidays)",
      "url": "https://www.gov.br/pt-br/calendario",
      "status": "completed",
      "last_verified": "2026-06-07",
      "verified_by": "auto",
      "details": {
        "假期类型": "Public",
        "固定日期": "否",
        "全国通用": "是"
      },
      "name_zh": "独立日",
      "description_zh": "独立日（巴西公众假期）"
    },
    {
      "id": "br-holiday-2025-our-lady-of-aparecida-10-12-public",
      "name": "Nossa Senhora Aparecida",
      "name_en": "Our Lady of Aparecida",
      "date": "2025-10-12",
      "end_date": "2025-10-12",
      "timezone": "America/Sao_Paulo",
      "type": "event",
      "year": 2025,
      "description": "Nossa Senhora Aparecida（巴西公众假期）",
      "description_en": "Our Lady of Aparecida (Brazil Public Holidays)",
      "url": "https://www.gov.br/pt-br/calendario",
      "status": "completed",
      "last_verified": "2026-06-07",
      "verified_by": "auto",
      "details": {
        "假期类型": "Public",
        "固定日期": "否",
        "全国通用": "是"
      },
      "name_zh": "圣母显灵节",
      "description_zh": "圣母显灵节（巴西公众假期）"
    },
    {
      "id": "br-holiday-2025-all-souls-day-11-02-public",
      "name": "Dia de Finados",
      "name_en": "All Souls' Day",
      "date": "2025-11-02",
      "end_date": "2025-11-02",
      "timezone": "America/Sao_Paulo",
      "type": "event",
      "year": 2025,
      "description": "Dia de Finados（巴西公众假期）",
      "description_en": "All Souls' Day (Brazil Public Holidays)",
      "url": "https://www.gov.br/pt-br/calendario",
      "status": "completed",
      "last_verified": "2026-06-07",
      "verified_by": "auto",
      "details": {
        "假期类型": "Public",
        "固定日期": "否",
        "全国通用": "是"
      },
      "name_zh": "亡灵节",
      "description_zh": "亡灵节（巴西公众假期）"
    },
    {
      "id": "br-holiday-2025-republic-proclamation-day-11-15-public",
      "name": "Proclamação da República",
      "name_en": "Republic Proclamation Day",
      "date": "2025-11-15",
      "end_date": "2025-11-15",
      "timezone": "America/Sao_Paulo",
      "type": "event",
      "year": 2025,
      "description": "Proclamação da República（巴西公众假期）",
      "description_en": "Republic Proclamation Day (Brazil Public Holidays)",
      "url": "https://www.gov.br/pt-br/calendario",
      "status": "completed",
      "last_verified": "2026-06-07",
      "verified_by": "auto",
      "details": {
        "假期类型": "Public",
        "固定日期": "否",
        "全国通用": "是"
      },
      "name_zh": "共和国宣言日",
      "description_zh": "共和国宣言日（巴西公众假期）"
    },
    {
      "id": "br-holiday-2025-black-awareness-day-11-20-public",
      "name": "Dia da Consciência Negra",
      "name_en": "Black Awareness Day",
      "date": "2025-11-20",
      "end_date": "2025-11-20",
      "timezone": "America/Sao_Paulo",
      "type": "event",
      "year": 2025,
      "description": "Dia da Consciência Negra（巴西公众假期）",
      "description_en": "Black Awareness Day (Brazil Public Holidays)",
      "url": "https://www.gov.br/pt-br/calendario",
      "status": "completed",
      "last_verified": "2026-06-07",
      "verified_by": "auto",
      "details": {
        "假期类型": "Public",
        "固定日期": "否",
        "全国通用": "是"
      },
      "name_zh": "黑人觉醒日",
      "description_zh": "黑人觉醒日（巴西公众假期）"
    },
    {
      "id": "br-holiday-2025-christmas-day-12-25-public",
      "name": "Natal",
      "name_en": "Christmas Day",
      "date": "2025-12-25",
      "end_date": "2025-12-25",
      "timezone": "America/Sao_Paulo",
      "type": "event",
      "year": 2025,
      "description": "Natal（巴西公众假期）",
      "description_en": "Christmas Day (Brazil Public Holidays)",
      "url": "https://www.gov.br/pt-br/calendario",
      "status": "completed",
      "last_verified": "2026-06-07",
      "verified_by": "auto",
      "details": {
        "假期类型": "Public",
        "固定日期": "否",
        "全国通用": "是"
      },
      "name_zh": "圣诞节",
      "description_zh": "圣诞节（巴西公众假期）"
    },
    {
      "id": "br-holiday-2026-new-years-day-01-01-public",
      "name": "Confraternização Universal",
      "name_en": "New Year's Day",
      "date": "2026-01-01",
      "end_date": "2026-01-01",
      "timezone": "America/Sao_Paulo",
      "type": "event",
      "year": 2026,
      "description": "Confraternização Universal（巴西公众假期）",
      "description_en": "New Year's Day (Brazil Public Holidays)",
      "url": "https://www.gov.br/pt-br/calendario",
      "status": "completed",
      "last_verified": "2026-06-07",
      "verified_by": "auto",
      "details": {
        "假期类型": "Public",
        "固定日期": "否",
        "全国通用": "是"
      },
      "name_zh": "元旦",
      "description_zh": "元旦（巴西公众假期）"
    },
    {
      "id": "br-holiday-2026-carnival-02-16-bank",
      "name": "Carnaval",
      "name_en": "Carnival",
      "date": "2026-02-16",
      "end_date": "2026-02-16",
      "timezone": "America/Sao_Paulo",
      "type": "event",
      "year": 2026,
      "description": "Carnaval（巴西公众假期）",
      "description_en": "Carnival (Brazil Public Holidays)",
      "url": "https://www.gov.br/pt-br/calendario",
      "status": "completed",
      "last_verified": "2026-06-07",
      "verified_by": "auto",
      "details": {
        "假期类型": "Bank, Optional",
        "固定日期": "否",
        "全国通用": "是"
      },
      "name_zh": "狂欢节",
      "description_zh": "狂欢节（巴西公众假期）"
    },
    {
      "id": "br-holiday-2026-carnival-02-17-bank",
      "name": "Carnaval",
      "name_en": "Carnival",
      "date": "2026-02-17",
      "end_date": "2026-02-17",
      "timezone": "America/Sao_Paulo",
      "type": "event",
      "year": 2026,
      "description": "Carnaval（巴西公众假期）",
      "description_en": "Carnival (Brazil Public Holidays)",
      "url": "https://www.gov.br/pt-br/calendario",
      "status": "completed",
      "last_verified": "2026-06-07",
      "verified_by": "auto",
      "details": {
        "假期类型": "Bank, Optional",
        "固定日期": "否",
        "全国通用": "是"
      },
      "name_zh": "狂欢节",
      "description_zh": "狂欢节（巴西公众假期）"
    },
    {
      "id": "br-holiday-2026-good-friday-04-03-public",
      "name": "Sexta-feira Santa",
      "name_en": "Good Friday",
      "date": "2026-04-03",
      "end_date": "2026-04-03",
      "timezone": "America/Sao_Paulo",
      "type": "event",
      "year": 2026,
      "description": "Sexta-feira Santa（巴西公众假期）",
      "description_en": "Good Friday (Brazil Public Holidays)",
      "url": "https://www.gov.br/pt-br/calendario",
      "status": "completed",
      "last_verified": "2026-06-07",
      "verified_by": "auto",
      "details": {
        "假期类型": "Public",
        "固定日期": "否",
        "全国通用": "是"
      },
      "name_zh": "耶稣受难日",
      "description_zh": "耶稣受难日（巴西公众假期）"
    },
    {
      "id": "br-holiday-2026-easter-sunday-04-05-public",
      "name": "Domingo de Páscoa",
      "name_en": "Easter Sunday",
      "date": "2026-04-05",
      "end_date": "2026-04-05",
      "timezone": "America/Sao_Paulo",
      "type": "event",
      "year": 2026,
      "description": "Domingo de Páscoa（巴西公众假期）",
      "description_en": "Easter Sunday (Brazil Public Holidays)",
      "url": "https://www.gov.br/pt-br/calendario",
      "status": "completed",
      "last_verified": "2026-06-07",
      "verified_by": "auto",
      "details": {
        "假期类型": "Public",
        "固定日期": "否",
        "全国通用": "是"
      },
      "name_zh": "复活节",
      "description_zh": "复活节（巴西公众假期）"
    },
    {
      "id": "br-holiday-2026-tiradentes-04-21-public",
      "name": "Dia de Tiradentes",
      "name_en": "Tiradentes",
      "date": "2026-04-21",
      "end_date": "2026-04-21",
      "timezone": "America/Sao_Paulo",
      "type": "event",
      "year": 2026,
      "description": "Dia de Tiradentes（巴西公众假期）",
      "description_en": "Tiradentes (Brazil Public Holidays)",
      "url": "https://www.gov.br/pt-br/calendario",
      "status": "completed",
      "last_verified": "2026-06-07",
      "verified_by": "auto",
      "details": {
        "假期类型": "Public",
        "固定日期": "否",
        "全国通用": "是"
      },
      "name_zh": "蒂拉登特斯日",
      "description_zh": "蒂拉登特斯日（巴西公众假期）"
    },
    {
      "id": "br-holiday-2026-labour-day-05-01-public",
      "name": "Dia do Trabalhador",
      "name_en": "Labour Day",
      "date": "2026-05-01",
      "end_date": "2026-05-01",
      "timezone": "America/Sao_Paulo",
      "type": "event",
      "year": 2026,
      "description": "Dia do Trabalhador（巴西公众假期）",
      "description_en": "Labour Day (Brazil Public Holidays)",
      "url": "https://www.gov.br/pt-br/calendario",
      "status": "completed",
      "last_verified": "2026-06-07",
      "verified_by": "auto",
      "details": {
        "假期类型": "Public",
        "固定日期": "否",
        "全国通用": "是"
      },
      "name_zh": "劳动节",
      "description_zh": "劳动节（巴西公众假期）"
    },
    {
      "id": "br-holiday-2026-corpus-christi-06-04-public",
      "name": "Corpus Christi",
      "name_en": "Corpus Christi",
      "date": "2026-06-04",
      "end_date": "2026-06-04",
      "timezone": "America/Sao_Paulo",
      "type": "event",
      "year": 2026,
      "description": "Corpus Christi（巴西公众假期）",
      "description_en": "Corpus Christi (Brazil Public Holidays)",
      "url": "https://www.gov.br/pt-br/calendario",
      "status": "completed",
      "last_verified": "2026-06-07",
      "verified_by": "auto",
      "details": {
        "假期类型": "Public",
        "固定日期": "否",
        "全国通用": "是"
      },
      "name_zh": "圣体节",
      "description_zh": "圣体节（巴西公众假期）"
    },
    {
      "id": "br-holiday-2026-constitutionalist-revolution-of-1932-07-09-br-sp",
      "name": "Revolução Constitucionalista de 1932",
      "name_en": "Constitutionalist Revolution of 1932",
      "date": "2026-07-09",
      "end_date": "2026-07-09",
      "timezone": "America/Sao_Paulo",
      "type": "event",
      "year": 2026,
      "description": "Revolução Constitucionalista de 1932（巴西公众假期）",
      "description_en": "Constitutionalist Revolution of 1932 (Brazil Public Holidays)",
      "url": "https://www.gov.br/pt-br/calendario",
      "status": "confirmed",
      "last_verified": "2026-06-07",
      "verified_by": "auto",
      "details": {
        "假期类型": "Public",
        "固定日期": "否",
        "全国通用": "否",
        "适用地区": "BR-SP"
      },
      "name_zh": "1932年宪政革命纪念日",
      "description_zh": "1932年宪政革命纪念日（巴西公众假期）"
    },
    {
      "id": "br-holiday-2026-independence-day-09-07-public",
      "name": "Dia da Independência",
      "name_en": "Independence Day",
      "date": "2026-09-07",
      "end_date": "2026-09-07",
      "timezone": "America/Sao_Paulo",
      "type": "event",
      "year": 2026,
      "description": "Dia da Independência（巴西公众假期）",
      "description_en": "Independence Day (Brazil Public Holidays)",
      "url": "https://www.gov.br/pt-br/calendario",
      "status": "confirmed",
      "last_verified": "2026-06-07",
      "verified_by": "auto",
      "details": {
        "假期类型": "Public",
        "固定日期": "否",
        "全国通用": "是"
      },
      "name_zh": "独立日",
      "description_zh": "独立日（巴西公众假期）"
    },
    {
      "id": "br-holiday-2026-our-lady-of-aparecida-10-12-public",
      "name": "Nossa Senhora Aparecida",
      "name_en": "Our Lady of Aparecida",
      "date": "2026-10-12",
      "end_date": "2026-10-12",
      "timezone": "America/Sao_Paulo",
      "type": "event",
      "year": 2026,
      "description": "Nossa Senhora Aparecida（巴西公众假期）",
      "description_en": "Our Lady of Aparecida (Brazil Public Holidays)",
      "url": "https://www.gov.br/pt-br/calendario",
      "status": "confirmed",
      "last_verified": "2026-06-07",
      "verified_by": "auto",
      "details": {
        "假期类型": "Public",
        "固定日期": "否",
        "全国通用": "是"
      },
      "name_zh": "圣母显灵节",
      "description_zh": "圣母显灵节（巴西公众假期）"
    },
    {
      "id": "br-holiday-2026-all-souls-day-11-02-public",
      "name": "Dia de Finados",
      "name_en": "All Souls' Day",
      "date": "2026-11-02",
      "end_date": "2026-11-02",
      "timezone": "America/Sao_Paulo",
      "type": "event",
      "year": 2026,
      "description": "Dia de Finados（巴西公众假期）",
      "description_en": "All Souls' Day (Brazil Public Holidays)",
      "url": "https://www.gov.br/pt-br/calendario",
      "status": "confirmed",
      "last_verified": "2026-06-07",
      "verified_by": "auto",
      "details": {
        "假期类型": "Public",
        "固定日期": "否",
        "全国通用": "是"
      },
      "name_zh": "亡灵节",
      "description_zh": "亡灵节（巴西公众假期）"
    },
    {
      "id": "br-holiday-2026-republic-proclamation-day-11-15-public",
      "name": "Proclamação da República",
      "name_en": "Republic Proclamation Day",
      "date": "2026-11-15",
      "end_date": "2026-11-15",
      "timezone": "America/Sao_Paulo",
      "type": "event",
      "year": 2026,
      "description": "Proclamação da República（巴西公众假期）",
      "description_en": "Republic Proclamation Day (Brazil Public Holidays)",
      "url": "https://www.gov.br/pt-br/calendario",
      "status": "confirmed",
      "last_verified": "2026-06-07",
      "verified_by": "auto",
      "details": {
        "假期类型": "Public",
        "固定日期": "否",
        "全国通用": "是"
      },
      "name_zh": "共和国宣言日",
      "description_zh": "共和国宣言日（巴西公众假期）"
    },
    {
      "id": "br-holiday-2026-black-awareness-day-11-20-public",
      "name": "Dia da Consciência Negra",
      "name_en": "Black Awareness Day",
      "date": "2026-11-20",
      "end_date": "2026-11-20",
      "timezone": "America/Sao_Paulo",
      "type": "event",
      "year": 2026,
      "description": "Dia da Consciência Negra（巴西公众假期）",
      "description_en": "Black Awareness Day (Brazil Public Holidays)",
      "url": "https://www.gov.br/pt-br/calendario",
      "status": "confirmed",
      "last_verified": "2026-06-07",
      "verified_by": "auto",
      "details": {
        "假期类型": "Public",
        "固定日期": "否",
        "全国通用": "是"
      },
      "name_zh": "黑人觉醒日",
      "description_zh": "黑人觉醒日（巴西公众假期）"
    },
    {
      "id": "br-holiday-2026-christmas-day-12-25-public",
      "name": "Natal",
      "name_en": "Christmas Day",
      "date": "2026-12-25",
      "end_date": "2026-12-25",
      "timezone": "America/Sao_Paulo",
      "type": "event",
      "year": 2026,
      "description": "Natal（巴西公众假期）",
      "description_en": "Christmas Day (Brazil Public Holidays)",
      "url": "https://www.gov.br/pt-br/calendario",
      "status": "confirmed",
      "last_verified": "2026-06-07",
      "verified_by": "auto",
      "details": {
        "假期类型": "Public",
        "固定日期": "否",
        "全国通用": "是"
      },
      "name_zh": "圣诞节",
      "description_zh": "圣诞节（巴西公众假期）"
    },
    {
      "id": "br-holiday-2027-new-years-day-01-01-public",
      "name": "Confraternização Universal",
      "name_en": "New Year's Day",
      "date": "2027-01-01",
      "end_date": "2027-01-01",
      "timezone": "America/Sao_Paulo",
      "type": "event",
      "year": 2027,
      "description": "Confraternização Universal（巴西公众假期）",
      "description_en": "New Year's Day (Brazil Public Holidays)",
      "url": "https://www.gov.br/pt-br/calendario",
      "status": "confirmed",
      "last_verified": "2026-06-07",
      "verified_by": "auto",
      "details": {
        "假期类型": "Public",
        "固定日期": "否",
        "全国通用": "是"
      },
      "name_zh": "元旦",
      "description_zh": "元旦（巴西公众假期）"
    },
    {
      "id": "br-holiday-2027-carnival-02-08-bank",
      "name": "Carnaval",
      "name_en": "Carnival",
      "date": "2027-02-08",
      "end_date": "2027-02-08",
      "timezone": "America/Sao_Paulo",
      "type": "event",
      "year": 2027,
      "description": "Carnaval（巴西公众假期）",
      "description_en": "Carnival (Brazil Public Holidays)",
      "url": "https://www.gov.br/pt-br/calendario",
      "status": "confirmed",
      "last_verified": "2026-06-07",
      "verified_by": "auto",
      "details": {
        "假期类型": "Bank, Optional",
        "固定日期": "否",
        "全国通用": "是"
      },
      "name_zh": "狂欢节",
      "description_zh": "狂欢节（巴西公众假期）"
    },
    {
      "id": "br-holiday-2027-carnival-02-09-bank",
      "name": "Carnaval",
      "name_en": "Carnival",
      "date": "2027-02-09",
      "end_date": "2027-02-09",
      "timezone": "America/Sao_Paulo",
      "type": "event",
      "year": 2027,
      "description": "Carnaval（巴西公众假期）",
      "description_en": "Carnival (Brazil Public Holidays)",
      "url": "https://www.gov.br/pt-br/calendario",
      "status": "confirmed",
      "last_verified": "2026-06-07",
      "verified_by": "auto",
      "details": {
        "假期类型": "Bank, Optional",
        "固定日期": "否",
        "全国通用": "是"
      },
      "name_zh": "狂欢节",
      "description_zh": "狂欢节（巴西公众假期）"
    },
    {
      "id": "br-holiday-2027-good-friday-03-26-public",
      "name": "Sexta-feira Santa",
      "name_en": "Good Friday",
      "date": "2027-03-26",
      "end_date": "2027-03-26",
      "timezone": "America/Sao_Paulo",
      "type": "event",
      "year": 2027,
      "description": "Sexta-feira Santa（巴西公众假期）",
      "description_en": "Good Friday (Brazil Public Holidays)",
      "url": "https://www.gov.br/pt-br/calendario",
      "status": "confirmed",
      "last_verified": "2026-06-07",
      "verified_by": "auto",
      "details": {
        "假期类型": "Public",
        "固定日期": "否",
        "全国通用": "是"
      },
      "name_zh": "耶稣受难日",
      "description_zh": "耶稣受难日（巴西公众假期）"
    },
    {
      "id": "br-holiday-2027-easter-sunday-03-28-public",
      "name": "Domingo de Páscoa",
      "name_en": "Easter Sunday",
      "date": "2027-03-28",
      "end_date": "2027-03-28",
      "timezone": "America/Sao_Paulo",
      "type": "event",
      "year": 2027,
      "description": "Domingo de Páscoa（巴西公众假期）",
      "description_en": "Easter Sunday (Brazil Public Holidays)",
      "url": "https://www.gov.br/pt-br/calendario",
      "status": "confirmed",
      "last_verified": "2026-06-07",
      "verified_by": "auto",
      "details": {
        "假期类型": "Public",
        "固定日期": "否",
        "全国通用": "是"
      },
      "name_zh": "复活节",
      "description_zh": "复活节（巴西公众假期）"
    },
    {
      "id": "br-holiday-2027-tiradentes-04-21-public",
      "name": "Dia de Tiradentes",
      "name_en": "Tiradentes",
      "date": "2027-04-21",
      "end_date": "2027-04-21",
      "timezone": "America/Sao_Paulo",
      "type": "event",
      "year": 2027,
      "description": "Dia de Tiradentes（巴西公众假期）",
      "description_en": "Tiradentes (Brazil Public Holidays)",
      "url": "https://www.gov.br/pt-br/calendario",
      "status": "confirmed",
      "last_verified": "2026-06-07",
      "verified_by": "auto",
      "details": {
        "假期类型": "Public",
        "固定日期": "否",
        "全国通用": "是"
      },
      "name_zh": "蒂拉登特斯日",
      "description_zh": "蒂拉登特斯日（巴西公众假期）"
    },
    {
      "id": "br-holiday-2027-labour-day-05-01-public",
      "name": "Dia do Trabalhador",
      "name_en": "Labour Day",
      "date": "2027-05-01",
      "end_date": "2027-05-01",
      "timezone": "America/Sao_Paulo",
      "type": "event",
      "year": 2027,
      "description": "Dia do Trabalhador（巴西公众假期）",
      "description_en": "Labour Day (Brazil Public Holidays)",
      "url": "https://www.gov.br/pt-br/calendario",
      "status": "confirmed",
      "last_verified": "2026-06-07",
      "verified_by": "auto",
      "details": {
        "假期类型": "Public",
        "固定日期": "否",
        "全国通用": "是"
      },
      "name_zh": "劳动节",
      "description_zh": "劳动节（巴西公众假期）"
    },
    {
      "id": "br-holiday-2027-corpus-christi-05-27-public",
      "name": "Corpus Christi",
      "name_en": "Corpus Christi",
      "date": "2027-05-27",
      "end_date": "2027-05-27",
      "timezone": "America/Sao_Paulo",
      "type": "event",
      "year": 2027,
      "description": "Corpus Christi（巴西公众假期）",
      "description_en": "Corpus Christi (Brazil Public Holidays)",
      "url": "https://www.gov.br/pt-br/calendario",
      "status": "confirmed",
      "last_verified": "2026-06-07",
      "verified_by": "auto",
      "details": {
        "假期类型": "Public",
        "固定日期": "否",
        "全国通用": "是"
      },
      "name_zh": "圣体节",
      "description_zh": "圣体节（巴西公众假期）"
    },
    {
      "id": "br-holiday-2027-constitutionalist-revolution-of-1932-07-09-br-sp",
      "name": "Revolução Constitucionalista de 1932",
      "name_en": "Constitutionalist Revolution of 1932",
      "date": "2027-07-09",
      "end_date": "2027-07-09",
      "timezone": "America/Sao_Paulo",
      "type": "event",
      "year": 2027,
      "description": "Revolução Constitucionalista de 1932（巴西公众假期）",
      "description_en": "Constitutionalist Revolution of 1932 (Brazil Public Holidays)",
      "url": "https://www.gov.br/pt-br/calendario",
      "status": "confirmed",
      "last_verified": "2026-06-07",
      "verified_by": "auto",
      "details": {
        "假期类型": "Public",
        "固定日期": "否",
        "全国通用": "否",
        "适用地区": "BR-SP"
      },
      "name_zh": "1932年宪政革命纪念日",
      "description_zh": "1932年宪政革命纪念日（巴西公众假期）"
    },
    {
      "id": "br-holiday-2027-independence-day-09-07-public",
      "name": "Dia da Independência",
      "name_en": "Independence Day",
      "date": "2027-09-07",
      "end_date": "2027-09-07",
      "timezone": "America/Sao_Paulo",
      "type": "event",
      "year": 2027,
      "description": "Dia da Independência（巴西公众假期）",
      "description_en": "Independence Day (Brazil Public Holidays)",
      "url": "https://www.gov.br/pt-br/calendario",
      "status": "confirmed",
      "last_verified": "2026-06-07",
      "verified_by": "auto",
      "details": {
        "假期类型": "Public",
        "固定日期": "否",
        "全国通用": "是"
      },
      "name_zh": "独立日",
      "description_zh": "独立日（巴西公众假期）"
    },
    {
      "id": "br-holiday-2027-our-lady-of-aparecida-10-12-public",
      "name": "Nossa Senhora Aparecida",
      "name_en": "Our Lady of Aparecida",
      "date": "2027-10-12",
      "end_date": "2027-10-12",
      "timezone": "America/Sao_Paulo",
      "type": "event",
      "year": 2027,
      "description": "Nossa Senhora Aparecida（巴西公众假期）",
      "description_en": "Our Lady of Aparecida (Brazil Public Holidays)",
      "url": "https://www.gov.br/pt-br/calendario",
      "status": "confirmed",
      "last_verified": "2026-06-07",
      "verified_by": "auto",
      "details": {
        "假期类型": "Public",
        "固定日期": "否",
        "全国通用": "是"
      },
      "name_zh": "圣母显灵节",
      "description_zh": "圣母显灵节（巴西公众假期）"
    },
    {
      "id": "br-holiday-2027-all-souls-day-11-02-public",
      "name": "Dia de Finados",
      "name_en": "All Souls' Day",
      "date": "2027-11-02",
      "end_date": "2027-11-02",
      "timezone": "America/Sao_Paulo",
      "type": "event",
      "year": 2027,
      "description": "Dia de Finados（巴西公众假期）",
      "description_en": "All Souls' Day (Brazil Public Holidays)",
      "url": "https://www.gov.br/pt-br/calendario",
      "status": "confirmed",
      "last_verified": "2026-06-07",
      "verified_by": "auto",
      "details": {
        "假期类型": "Public",
        "固定日期": "否",
        "全国通用": "是"
      },
      "name_zh": "亡灵节",
      "description_zh": "亡灵节（巴西公众假期）"
    },
    {
      "id": "br-holiday-2027-republic-proclamation-day-11-15-public",
      "name": "Proclamação da República",
      "name_en": "Republic Proclamation Day",
      "date": "2027-11-15",
      "end_date": "2027-11-15",
      "timezone": "America/Sao_Paulo",
      "type": "event",
      "year": 2027,
      "description": "Proclamação da República（巴西公众假期）",
      "description_en": "Republic Proclamation Day (Brazil Public Holidays)",
      "url": "https://www.gov.br/pt-br/calendario",
      "status": "confirmed",
      "last_verified": "2026-06-07",
      "verified_by": "auto",
      "details": {
        "假期类型": "Public",
        "固定日期": "否",
        "全国通用": "是"
      },
      "name_zh": "共和国宣言日",
      "description_zh": "共和国宣言日（巴西公众假期）"
    },
    {
      "id": "br-holiday-2027-black-awareness-day-11-20-public",
      "name": "Dia da Consciência Negra",
      "name_en": "Black Awareness Day",
      "date": "2027-11-20",
      "end_date": "2027-11-20",
      "timezone": "America/Sao_Paulo",
      "type": "event",
      "year": 2027,
      "description": "Dia da Consciência Negra（巴西公众假期）",
      "description_en": "Black Awareness Day (Brazil Public Holidays)",
      "url": "https://www.gov.br/pt-br/calendario",
      "status": "confirmed",
      "last_verified": "2026-06-07",
      "verified_by": "auto",
      "details": {
        "假期类型": "Public",
        "固定日期": "否",
        "全国通用": "是"
      },
      "name_zh": "黑人觉醒日",
      "description_zh": "黑人觉醒日（巴西公众假期）"
    },
    {
      "id": "br-holiday-2027-christmas-day-12-25-public",
      "name": "Natal",
      "name_en": "Christmas Day",
      "date": "2027-12-25",
      "end_date": "2027-12-25",
      "timezone": "America/Sao_Paulo",
      "type": "event",
      "year": 2027,
      "description": "Natal（巴西公众假期）",
      "description_en": "Christmas Day (Brazil Public Holidays)",
      "url": "https://www.gov.br/pt-br/calendario",
      "status": "confirmed",
      "last_verified": "2026-06-07",
      "verified_by": "auto",
      "details": {
        "假期类型": "Public",
        "固定日期": "否",
        "全国通用": "是"
      },
      "name_zh": "圣诞节",
      "description_zh": "圣诞节（巴西公众假期）"
    }
  ],
  "last_updated": "2026-06-07"
}